cobol_parser/__init__.py
cobol_parser/cli.py
cobol_parser/interface.py
cobol_parser/logger.py
cobol_parser/parser.py
cobol_parser/extractors/__init__.py
cobol_parser/extractors/base_extractor.py
cobol_parser/extractors/call_extractor.py
cobol_parser/extractors/copybook_extractor.py
cobol_parser/extractors/io_extractor.py
cobol_parser/extractors/perform_extractor.py
cobol_parser/extractors/sql_extractor.py
cobol_parser/extractors/utils.py
legacylens_cobol_parser-0.1.20.dist-info/METADATA
legacylens_cobol_parser-0.1.20.dist-info/WHEEL
legacylens_cobol_parser-0.1.20.dist-info/top_level.txt
legacylens_cobol_parser-0.1.20.dist-info/RECORD
