Metadata-Version: 2.4
Name: legacylens_cobol_parser
Version: 0.1.20
Summary: A tool to extract information from COBOL programs
Author-email: Samuel Dion <sam94dion@gmail.com>
License: MIT
Project-URL: Homepage, https://github.com/sam94dion/legacylens-cobol-parser
Project-URL: Bug Tracker, https://github.com/sam94dion/legacylens-cobol-parser/issues
Classifier: Programming Language :: Python :: 3
Classifier: License :: OSI Approved :: MIT License
Classifier: Operating System :: OS Independent
Classifier: Development Status :: 4 - Beta
Classifier: Intended Audience :: Developers
Classifier: Topic :: Software Development :: Libraries :: Python Modules
Requires-Python: >=3.7
Requires-Dist: typing-extensions>=3.7.4
Provides-Extra: dev
Requires-Dist: pytest>=6.0.0; extra == "dev"
Requires-Dist: pytest-cov>=2.10.0; extra == "dev"
Requires-Dist: black>=20.8b1; extra == "dev"
Requires-Dist: flake8>=3.8.0; extra == "dev"
